MANIFEST.in
README.rst
setup.cfg
setup.py
djvue/__init__.py
djvue/apps.py
djvue/autocomplete.py
djvue/fields.py
djvue/forms.py
djvue/metadata.py
djvue/relations.py
djvue/routers.py
djvue/serializers.py
djvue/utils.py
djvue/viewsets.py
djvue/docs/Makefile
djvue/docs/README.md
djvue/docs/make.bat
djvue/docs/build/doctrees/environment.pickle
djvue/docs/build/doctrees/index.doctree
djvue/docs/build/doctrees/sections/Installation.doctree
djvue/docs/build/html/.buildinfo
djvue/docs/build/html/genindex.html
djvue/docs/build/html/index.html
djvue/docs/build/html/objects.inv
djvue/docs/build/html/search.html
djvue/docs/build/html/searchindex.js
djvue/docs/build/html/_sources/index.rst.txt
djvue/docs/build/html/_sources/sections/Installation.rst.txt
djvue/docs/build/html/_static/basic.css
djvue/docs/build/html/_static/doctools.js
djvue/docs/build/html/_static/documentation_options.js
djvue/docs/build/html/_static/file.png
djvue/docs/build/html/_static/jquery-3.5.1.js
djvue/docs/build/html/_static/jquery.js
djvue/docs/build/html/_static/language_data.js
djvue/docs/build/html/_static/minus.png
djvue/docs/build/html/_static/plus.png
djvue/docs/build/html/_static/pygments.css
djvue/docs/build/html/_static/searchtools.js
djvue/docs/build/html/_static/underscore-1.3.1.js
djvue/docs/build/html/_static/underscore.js
djvue/docs/build/html/sections/Installation.html
djvue/docs/source/__init__.py
djvue/docs/source/conf.py
djvue/docs/source/index.rst
djvue/docs/source/sections/Backend.rst
djvue/docs/source/sections/CommonRecipes.rst
djvue/docs/source/sections/DjVueFields.rst
djvue/docs/source/sections/Frontend.rst
djvue/docs/source/sections/Installation.rst
djvue/docs/source/sections/shelve.rst
djvue/static/djvue/.gitignore
djvue/static/djvue/README.md
djvue/static/djvue/package-lock.json
djvue/static/djvue/package.json
djvue/static/djvue/tsconfig.json
djvue/static/djvue/vue.config.js
djvue/static/djvue/yarn.lock
djvue/static/djvue/dist/demo.html
djvue/static/djvue/dist/djvue.common.js
djvue_framework.egg-info/PKG-INFO
djvue_framework.egg-info/SOURCES.txt
djvue_framework.egg-info/dependency_links.txt
djvue_framework.egg-info/top_level.txt