Metadata-Version: 1.1
Name: djvue-framework
Version: 1.1.2
Summary: Django djvue.
Home-page: UNKNOWN
Author: Pagina46
Author-email: info@pagina46.it
License: UNKNOWN
Platform: UNKNOWN
Classifier: Environment :: Web Environment
Classifier: Framework :: Django
Classifier: Intended Audience :: Developers
Classifier: Operating System :: OS Independent
Classifier: Programming Language :: Python
Classifier: Programming Language :: Python :: 3
Classifier: Topic :: Internet :: WWW/HTTP
